problem3_vending/vending_mealy.v
module vending_mealy(
    input  wire clk,
    input  wire rst,       
    input  wire [1:0] coin, // 01=5, 10=10, 00=idle, 11=ignore
    output reg  vend,  
    output reg  chg5       
);

    // State encoding (represents total so far)
    parameter total_0  = 2'b00; // total=0
    parameter total_5  = 2'b01; // total=5
    parameter total_10 = 2'b10; // total=10
    parameter total_15 = 2'b11; // total=15

    reg [1:0] state_present, state_next;

    // Register coin to avoid timing glitches
    reg [1:0] coin_reg;
    always @(posedge clk) begin
        if (rst) coin_reg <= 2'b00;
        else     coin_reg <= coin;
    end

    // State register
    always @(posedge clk) begin
        if (rst) state_present <= total_0;
        else     state_present <= state_next;
    end

    // Next-state and output logic (Mealy)
    always @(*) begin
        // defaults
        state_next = state_present;
        vend   = 0;
        chg5       = 0;

        case (state_present)
            total_0: case (coin_reg)
                    2'b01: state_next = total_5;
                    2'b10: state_next = total_10;
                    default: state_next = total_0;
                endcase

            total_5: case (coin_reg)
                    2'b01: state_next = total_10;
                    2'b10: state_next = total_15;
                    default: state_next = total_5;
                endcase

            total_10: case (coin_reg)
                    2'b01: state_next = total_15;
                    2'b10: begin
                              vend   = 1; // total=20
                              state_next = total_0;
                           end
                    default: state_next = total_10;
                endcase

            total_15: case (coin_reg)
                    2'b01: begin
                              vend   = 1; // total=20
                              state_next = total_0;
                           end
                    2'b10: begin
                              vend   = 1; // total=25
                              chg5       = 1;
                              state_next = total_0;
                           end
                    default: state_next = total_15;
                endcase
        endcase
    end
endmodule

problem3_vending/tb_vending_mealy.v
`timescale 1ns/1ps
module tb_vending_mealy;
    reg clk, rst;
    reg [1:0] coin;
    wire vend, chg5;

    vending_mealy dut(.clk(clk), .rst(rst), .coin(coin), .vend(vend), .chg5(chg5));

    always #5 clk = ~clk;

    initial begin
        clk = 0; rst = 1; coin = 2'b00;

        $dumpfile("dump.vcd");
        $dumpvars(0, tb_vending_mealy);

        // release reset
        repeat (2) @(negedge clk);
        rst = 0;

        // Scenario 1: 10 + 10 → vend
        send_coin(2'b10);
        send_coin(2'b10);

        // Scenario 2: 5 + 5 + 10 → vend
        send_coin(2'b01);
        send_coin(2'b01);
        send_coin(2'b10);

        // Scenario 3: 5 + 10 + 10 → vend + change
        send_coin(2'b01);
        send_coin(2'b10);
        send_coin(2'b10);

        // idle a few cycles
        repeat (5) @(negedge clk);

        $finish;
    end

    task send_coin;
        input [1:0] c;
        begin
            @(negedge clk);
            coin = c;         // apply coin
            @(posedge clk);   // hold across one full posedge
            @(negedge clk);
            coin = 2'b00;     // return to idle
        end
    endtask

endmodule

problem3_vending/dump.vcd
$date
	Tue Aug 19 01:38:10 2025
$end
$version
	Icarus Verilog
$end
$timescale
	1ps
$end
$scope module tb_vending_mealy $end
$var wire 1 ! vend $end
$var wire 1 " chg5 $end
$var reg 1 # clk $end
$var reg 2 $ coin [1:0] $end
$var reg 1 % rst $end
$scope module dut $end
$var wire 1 # clk $end
$var wire 2 & coin [1:0] $end
$var wire 1 % rst $end
$var parameter 2 ' total_0 $end
$var parameter 2 ( total_10 $end
$var parameter 2 ) total_15 $end
$var parameter 2 * total_5 $end
$var reg 1 " chg5 $end
$var reg 2 + coin_reg [1:0] $end
$var reg 2 , state_next [1:0] $end
$var reg 2 - state_present [1:0] $end
$var reg 1 ! vend $end
$upscope $end
$scope task send_coin $end
$var reg 2 . c [1:0] $end
$upscope $end
$upscope $end
$enddefinitions $end
$comment Show the parameter values. $end
$dumpall
b1 *
b11 )
b10 (
b0 '
$end
#0
$dumpvars
bx .
bx -
bx ,
bx +
b0 &
1%
b0 $
0#
x"
x!
$end
#5000
0"
0!
b0 ,
b0 +
b0 -
1#
#10000
0#
#15000
1#
#20000
b10 .
0%
0#
#25000
1#
#30000
b10 $
b10 &
0#
#35000
b10 ,
b10 +
1#
#40000
b0 $
b0 &
0#
#45000
b0 +
b10 -
1#
#50000
b10 $
b10 &
0#
#55000
b0 ,
1!
b10 +
1#
#60000
b1 .
b0 $
b0 &
0#
#65000
0!
b0 +
b0 -
1#
#70000
b1 $
b1 &
0#
#75000
b1 ,
b1 +
1#
#80000
b0 $
b0 &
0#
#85000
b0 +
b1 -
1#
#90000
b1 $
b1 &
0#
#95000
b10 ,
b1 +
1#
#100000
b10 .
b0 $
b0 &
0#
#105000
b0 +
b10 -
1#
#110000
b10 $
b10 &
0#
#115000
b0 ,
1!
b10 +
1#
#120000
b1 .
b0 $
b0 &
0#
#125000
0!
b0 +
b0 -
1#
#130000
b1 $
b1 &
0#
#135000
b1 ,
b1 +
1#
#140000
b10 .
b0 $
b0 &
0#
#145000
b0 +
b1 -
1#
#150000
b10 $
b10 &
0#
#155000
b11 ,
b10 +
1#
#160000
b0 $
b0 &
0#
#165000
b0 +
b11 -
1#
#170000
b10 $
b10 &
0#
#175000
b0 ,
1"
1!
b10 +
1#
#180000
b0 $
b0 &
0#
#185000
0"
0!
b0 +
b0 -
1#
