fsm-assignments/problem1_seqdet/seq_det_mealy.v
module seq_detect_mealy(input clk, input reset, input din, output reg y);
    reg [1:0] state_present, state_next;

    parameter match_0 = 2'b00; // no match
    parameter match_1 = 2'b01; // saw "1"
    parameter match_2 = 2'b10; // saw "11"
    parameter match_3 = 2'b11; // saw "110"

    always @(posedge clk) begin
        if (reset) state_present <= match_0;   
        else  state_present <= state_next;
    end

    always @(*) begin
        y = 1'b0;           // default output
        state_next = match_0;    // default next state

        case (state_present)
            match_0: begin
                if (din) state_next = match_1;
                else     state_next = match_0;
            end
            match_1: begin
                if (din) state_next = match_2;
                else     state_next = match_0;
            end
            match_2: begin
                if (din) state_next = match_2; // stay with suffix "11"
                else     state_next = match_3;
            end
            match_3: begin
                if (din) begin
                    y = 1'b1;            // detected 1101
                    state_next = match_1;     // back suffix "1"
                end else begin
                    state_next = match_0;
                end
            end
            default: state_next = match_0;
        endcase
    end
endmodule

fsm-assignments/problem1_seqdet/tb_seq_detect_mealy.v
`timescale 1ns/1ps
module tb_seq_detect_mealy;
    reg clk, rst, din;
    wire y;

    seq_detect_mealy dut(.clk(clk), .reset(rst), .din(din), .y(y));

    always #5 clk = ~clk;

    initial begin
        // Init
        clk = 0;
        rst = 1;
        din = 0;

        $dumpfile("dump.vcd");
        $dumpvars(0, tb_seq_detect_mealy);

        // Hold reset for 2 cycles
        repeat (2) @(negedge clk);
        rst = 0;

        // Drive a bitstream with overlaps: 11011011101
        send_bit(1); send_bit(1); send_bit(0); send_bit(1);
        send_bit(1); send_bit(0); send_bit(1);
        send_bit(1); send_bit(1); send_bit(0); send_bit(1);

        repeat (5) @(negedge clk);

        $finish;
    end

    // Task to send one bit per cycle
    task send_bit;
        input b;
        begin
            @(negedge clk);
            din = b;
        end
    endtask
endmodule

fsm-assignments/problem1_seqdet/dump.vcd
$date
	Tue Aug 19 15:44:46 2025
$end
$version
	Icarus Verilog
$end
$timescale
	1ps
$end
$scope module tb_seq_detect_mealy $end
$var wire 1 ! y $end
$var reg 1 " clk $end
$var reg 1 # din $end
$var reg 1 $ rst $end
$scope module dut $end
$var wire 1 " clk $end
$var wire 1 # din $end
$var wire 1 $ reset $end
$var parameter 2 % match_0 $end
$var parameter 2 & match_1 $end
$var parameter 2 ' match_2 $end
$var parameter 2 ( match_3 $end
$var reg 2 ) state_next [1:0] $end
$var reg 2 * state_present [1:0] $end
$var reg 1 ! y $end
$upscope $end
$scope task send_bit $end
$var reg 1 + b $end
$upscope $end
$upscope $end
$enddefinitions $end
$comment Show the parameter values. $end
$dumpall
b11 (
b10 '
b1 &
b0 %
$end
#0
$dumpvars
x+
bx *
b0 )
1$
0#
0"
0!
$end
#5000
b0 *
1"
#10000
0"
#15000
1"
#20000
1+
0$
0"
#25000
1"
#30000
b1 )
1#
0"
#35000
b10 )
b1 *
1"
#40000
0+
0"
#45000
b10 )
b10 *
1"
#50000
b11 )
1+
0#
0"
#55000
b0 )
b11 *
1"
#60000
b1 )
1!
1#
0"
#65000
b10 )
0!
b1 *
1"
#70000
0+
0"
#75000
b10 )
b10 *
1"
#80000
b11 )
1+
0#
0"
#85000
b0 )
b11 *
1"
#90000
b1 )
1!
1#
0"
#95000
b10 )
0!
b1 *
1"
#100000
0"
#105000
b10 )
b10 *
1"
#110000
0+
0"
#115000
1"
#120000
b11 )
1+
0#
0"
#125000
b0 )
b11 *
1"
#130000
b1 )
1!
1#
0"
#135000
b10 )
0!
b1 *
1"
#140000
0"
#145000
b10 )
b10 *
1"
